test_mark/__init__.py
test_mark/print_text.py
test_mark-0.1.dist-info/LICENSE
test_mark-0.1.dist-info/METADATA
test_mark-0.1.dist-info/WHEEL
test_mark-0.1.dist-info/top_level.txt
test_mark-0.1.dist-info/RECORD
